LICENSE.txt
README.md
setup.cfg
setup.py
vsco_scraper.egg-info/PKG-INFO
vsco_scraper.egg-info/SOURCES.txt
vsco_scraper.egg-info/dependency_links.txt
vsco_scraper.egg-info/entry_points.txt
vsco_scraper.egg-info/requires.txt
vsco_scraper.egg-info/top_level.txt
vscoscrape/__init__.py
vscoscrape/constants.py
vscoscrape/vscoscrape.py