Metadata-Version: 1.0
Name: vsco-scraper
Version: 0.55
Summary: Scrape a user's VSCO profile data
Home-page: https://github.com/mvabdi/vsco-scraper
Author: Mustafa Abdi
Author-email: mustafabyabdi@gmail.com
License: UNKNOWN
Keywords: vsco scrape image images download
Platform: UNKNOWN
